typed_environment_configuration/__init__.py
typed_environment_configuration/typed_environment_configuration.py
typed_environment_configuration-0.1.5.dist-info/DESCRIPTION.rst
typed_environment_configuration-0.1.5.dist-info/METADATA
typed_environment_configuration-0.1.5.dist-info/RECORD
typed_environment_configuration-0.1.5.dist-info/WHEEL
typed_environment_configuration-0.1.5.dist-info/metadata.json
typed_environment_configuration-0.1.5.dist-info/top_level.txt
