Metadata-Version: 2.0
Name: typed-environment-configuration
Version: 0.1.5
Summary: Environment-based configuration
Home-page: https://github.com/springload/typed_environment_configuration
Author: Eugene Dementyev
Author-email: eugene@springload.co.nz
License: MIT license
Keywords: typed_environment_configuration
Platform: UNKNOWN
Classifier: Development Status :: 2 - Pre-Alpha
Classifier: Intended Audience :: Developers
Classifier: License :: OSI Approved :: MIT License
Classifier: Natural Language :: English
Classifier: Programming Language :: Python :: 3
Classifier: Programming Language :: Python :: 3.4
Classifier: Programming Language :: Python :: 3.5
Classifier: Programming Language :: Python :: 3.6
Classifier: Programming Language :: Python :: 3.7
License-File: LICENSE
License-File: AUTHORS.rst
Requires-Dist: typepy (==1.3.0)
